guardian_queryset/__init__.py
guardian_queryset/admin.py
guardian_queryset/apps.py
guardian_queryset/decorators.py
guardian_queryset/filters.py
guardian_queryset/manager.py
guardian_queryset/models.py
guardian_queryset/permission_backends.py
guardian_queryset/queryset.py
guardian_queryset/serializers.py
guardian_queryset/utils.py
guardian_queryset/views.py
guardian_queryset/migrations/__init__.py
django_guardian_queryset-1.0.16.dist-info/METADATA
django_guardian_queryset-1.0.16.dist-info/WHEEL
django_guardian_queryset-1.0.16.dist-info/top_level.txt
django_guardian_queryset-1.0.16.dist-info/RECORD
